islandkit/__init__.py
islandkit/config.py
islandkit/tqdm.py
islandkit-0.1.0.dist-info/licenses/LICENSE
islandkit-0.1.0.dist-info/METADATA
islandkit-0.1.0.dist-info/WHEEL
islandkit-0.1.0.dist-info/top_level.txt
islandkit-0.1.0.dist-info/RECORD
