Metadata-Version: 2.4
Name: islandkit
Version: 0.1.0
Summary: Your TQDM on dynamic island - Remote progress tracking for Python long-running tasks
Author-email: Siyuan Yu <yusiyuan@hextechsz.com>
Maintainer-email: Siyuan Yu <yusiyuan@hextechsz.com>
License: MIT
Project-URL: Homepage, https://github.com/siyryu/IslandKit-python
Project-URL: Repository, https://github.com/siyryu/IslandKit-python
Project-URL: Issues, https://github.com/siyryu/IslandKit-python/issues
Project-URL: Documentation, https://github.com/siyryu/IslandKit-python#readme
Keywords: tqdm,progress,monitoring,supabase,realtime
Classifier: Development Status :: 3 - Alpha
Classifier: Intended Audience :: Developers
Classifier: License :: OSI Approved :: MIT License
Classifier: Programming Language :: Python :: 3
Classifier: Programming Language :: Python :: 3.8
Classifier: Programming Language :: Python :: 3.9
Classifier: Programming Language :: Python :: 3.10
Classifier: Programming Language :: Python :: 3.11
Classifier: Programming Language :: Python :: 3.12
Classifier: Topic :: Software Development :: Libraries :: Python Modules
Classifier: Topic :: System :: Monitoring
Requires-Python: >=3.8
License-File: LICENSE
Requires-Dist: tqdm>=4.64.0
Requires-Dist: supabase>=2.0.0
Requires-Dist: httpx>=0.24.0
Requires-Dist: realtime>=1.0.0
Provides-Extra: dev
Requires-Dist: pytest>=7.0.0; extra == "dev"
Requires-Dist: pytest-asyncio>=0.21.0; extra == "dev"
Requires-Dist: black>=23.0.0; extra == "dev"
Requires-Dist: flake8>=5.0.0; extra == "dev"
Requires-Dist: mypy>=1.0.0; extra == "dev"
Requires-Dist: build>=0.10.0; extra == "dev"
Requires-Dist: twine>=4.0.0; extra == "dev"
Dynamic: license-file
